{
  "update": "16:36:31 20.02.2017",
  "courses": [
    {
      "id": "StudyIntonation",
      "title": "Study Intonation",
      "description": "This course is for everyday discourse skills mastering. Meet the principle tones of English. Learn to produce them when speaking. Starting with quite short common phrases you will browse through a variety of speaking patterns to feel and train the melody of English speech",
      "logoUrl": "https://github.com/bogach/prof-courses/raw/master/StudyIntonation/null",
      "size": 1362845,
      "difficulty": 1,
      "category": "Everyday discourse",
      "version": "v1.1.1",
      "sha2Hash": "bc9de589336238922eb49d0e35b7b287417bca03de01b46d090f9df34bc34a9",
      "url": "https://github.com/bogach/prof-courses/releases/download/v1.1.1/StudyIntonation.zip",
      "authors": [
        "Bogach Natalia",
        "Dyachkov Vadim",
        "Lamtev Anton",
        "Lezhenin Yurij",
        "Vylegzhanina Karina"
      ],
      "releaseDate": "18.02.2017"
    },
    {
      "id": "CrashCourse",
      "title": "Crash Course",
      "description": "Meet the principle tones of English. Learn to produce them when speaking. Starting with quite short common phrases you will browse through a variety of speaking patterns to feel and train the melody of English speech",
      "logoUrl": "https://github.com/bogach/prof-courses/raw/master/CrashCourse/null",
      "size": 423835,
      "difficulty": 3,
      "category": "Example",
      "version": "v1.1.1",
      "sha2Hash": "d4806f679f4a103d8ced858a9c861d4b8d03da886913ce329eb3b64ecd20b4",
      "url": "https://github.com/bogach/prof-courses/releases/download/v1.1.1/CrashCourse.zip",
      "authors": [
        "Bogach Natalia",
        "Dyachkov Vadim",
        "Lamtev Anton",
        "Lezhenin Yurij",
        "Vylegzhanina Karina"
      ],
      "releaseDate": "18.02.2017"
    },
    {
      "id": "DemoCourse",
      "title": "Demo Course",
      "description": "Meet the principle tones of English. Learn to produce them when speaking. Starting with quite short common phrases you will browse through a variety of speaking patterns to feel and train the melody of English speech",
      "logoUrl": "https://github.com/bogach/prof-courses/raw/master/DemoCourse/null",
      "size": 423763,
      "difficulty": 2,
      "category": "Example",
      "version": "v1.1.1",
      "sha2Hash": "1a5ced5662458fa54fa44ebba5fe3ed89275a9d71db2bca6aedee24499e3761e",
      "url": "https://github.com/bogach/prof-courses/releases/download/v1.1.1/DemoCourse.zip",
      "authors": [
        "Bogach Natalia",
        "Dyachkov Vadim",
        "Lamtev Anton",
        "Lezhenin Yurij",
        "Vylegzhanina Karina"
      ],
      "releaseDate": "18.02.2017"
    }
  ]
}
